[
  {
    "字段名": "id",
    "类型": "BIGINT",
    "约束": "主键、自增、非空",
    "说明": "角色唯一标识符"
  },
  {
    "字段名": "name",
    "类型": "VARCHAR(50)",
    "约束": "非空",
    "说明": "角色名称（普通用户/教练/管理员）"
  },
  {
    "字段名": "description",
    "类型": "VARCHAR(255)",
    "约束": "",
    "说明": "角色描述信息"
  },
  {
    "字段名": "permissions",
    "类型": "TEXT",
    "约束": "",
    "说明": "角色权限列表（JSON格式）"
  },
  {
    "字段名": "create_time",
    "类型": "DATETIME",
    "约束": "默认当前时间",
    "说明": "角色创建时间"
  },
  {
    "字段名": "update_time",
    "类型": "DATETIME",
    "约束": "自动更新",
    "说明": "最后更新时间"
  },
  {
    "字段名": "is_delete",
    "类型": "TINYINT",
    "约束": "默认值0",
    "说明": "是否删除：0-未删除 1-已删除"
  }
]