{
  "title": "系统管理员角色用例",
  "text": "展示系统管理员的高级管理用例（系统配置、权限管理、数据维护等）与管理边界。",
  "imagePath": "${uml}/usecase-system.png",
  "word_limit": 120,
  "content": "系统管理员角色作为最高权限级别的用户，其用例图侧重于系统级的配置管理和深层次的维护操作。核心用例包括系统配置管理（系统参数设置、性能阈值配置、安全策略设定）、权限管理（角色权限配置、管理员权限分配、系统访问控制）、数据维护（数据备份与恢复、数据库维护、日志管理）和系统监控（性能监控、安全事件监测、系统健康检查）等。管理边界严格限定了系统管理员的操作范围，不允许直接操作业务数据，不允许越权访问用户隐私信息，不允许绕过审计机制进行敏感操作。",
  "id": "2.2.3.3",
  "parentChapter": "2.2.3",
  "sourceFile": "chapter.2.2.3.json",
  "extractedAt": "2025-09-29T13:54:23.215Z"
}